{
  "minecraft:recipes/decorations/purple_stained_glass_pane": {
    "criteria": {
      "has_glass": "2020-05-09 20:07:43 -0700"
    },
    "done": true
  },
  "minecraft:recipes/building_blocks/brick_stairs_from_bricks_stonecutting": {
    "criteria": {
      "has_bricks": "2020-05-02 22:18:17 -0700"
    },
    "done": true
  },
  "minecraft:recipes/building_blocks/polished_andesite_slab": {
    "criteria": {
      "has_polished_andesite": "2020-05-04 21:50:42 -0700"
    },
    "done": true
  },
  "minecraft:recipes/building_blocks/black_stained_glass": {
    "criteria": {
      "has_glass": "2020-05-09 20:07:43 -0700"
    },
    "done": true
  },
  "minecraft:recipes/building_blocks/quartz_pillar": {
    "criteria": {
      "has_quartz_block": "2020-05-02 22:25:01 -0700"
    },
    "done": true
  },
  "minecraft:recipes/redstone/lever": {
    "criteria": {
      "has_cobblestone": "2020-05-14 15:55:32 -0700"
    },
    "done": true
  },
  "minecraft:recipes/building_blocks/cobblestone_stairs_from_cobblestone_stonecutting": {
    "criteria": {
      "has_cobblestone": "2020-05-14 15:55:32 -0700"
    },
    "done": true
  },
  "minecraft:recipes/decorations/brick_wall": {
    "criteria": {
      "has_bricks": "2020-05-02 22:18:17 -0700"
    },
    "done": true
  },
  "minecraft:recipes/building_blocks/stone_bricks": {
    "criteria": {
      "has_stone": "2020-05-02 23:02:14 -0700"
    },
    "done": true
  },
  "minecraft:recipes/misc/writable_book": {
    "criteria": {
      "has_book": "2020-05-08 19:41:49 -0700"
    },
    "done": true
  },
  "minecraft:recipes/building_blocks/dark_prismarine_slab_from_dark_prismarine_stonecutting": {
    "criteria": {
      "has_dark_prismarine": "2020-05-04 22:04:50 -0700"
    },
    "done": true
  },
  "minecraft:recipes/building_blocks/polished_andesite_stairs": {
    "criteria": {
      "has_polished_andesite": "2020-05-04 21:50:42 -0700"
    },
    "done": true
  },
  "minecraft:recipes/building_blocks/polished_andesite_stairs_from_andesite_stonecutting": {
    "criteria": {
      "has_andesite": "2020-05-09 20:07:21 -0700"
    },
    "done": true
  },
  "minecraft:recipes/building_blocks/gray_stained_glass": {
    "criteria": {
      "has_glass": "2020-05-09 20:07:43 -0700"
    },
    "done": true
  },
  "minecraft:recipes/redstone/birch_pressure_plate": {
    "criteria": {
      "has_planks": "2020-05-14 15:54:34 -0700"
    },
    "done": true
  },
  "minecraft:recipes/decorations/campfire": {
    "criteria": {
      "has_stick": "2020-05-02 22:49:36 -0700"
    },
    "done": true
  },
  "minecraft:recipes/decorations/crafting_table": {
    "criteria": {
      "has_planks": "2020-05-14 15:54:34 -0700"
    },
    "done": true
  },
  "minecraft:recipes/building_blocks/purple_stained_glass": {
    "criteria": {
      "has_glass": "2020-05-09 20:07:43 -0700"
    },
    "done": true
  },
  "minecraft:recipes/building_blocks/diorite_slab_from_diorite_stonecutting": {
    "criteria": {
      "has_diorite": "2020-05-02 22:33:27 -0700"
    },
    "done": true
  },
  "minecraft:recipes/building_blocks/smooth_stone": {
    "criteria": {
      "has_stone": "2020-05-02 23:02:14 -0700"
    },
    "done": true
  },
  "minecraft:recipes/decorations/blast_furnace": {
    "criteria": {
      "has_smooth_stone": "2020-05-02 22:18:44 -0700"
    },
    "done": true
  },
  "minecraft:recipes/decorations/ladder": {
    "criteria": {
      "has_stick": "2020-05-02 22:49:36 -0700"
    },
    "done": true
  },
  "minecraft:recipes/decorations/lime_stained_glass_pane": {
    "criteria": {
      "has_glass": "2020-05-09 20:07:43 -0700"
    },
    "done": true
  },
  "minecraft:recipes/building_blocks/dark_prismarine_stairs_from_dark_prismarine_stonecutting": {
    "criteria": {
      "has_dark_prismarine": "2020-05-04 22:04:50 -0700"
    },
    "done": true
  },
  "minecraft:recipes/decorations/chest": {
    "criteria": {
      "has_lots_of_items": "2020-04-21 22:29:55 -0700"
    },
    "done": true
  },
  "minecraft:story/shiny_gear": {
    "criteria": {
      "diamond_helmet": "2020-05-05 00:13:09 -0700"
    },
    "done": true
  },
  "minecraft:recipes/building_blocks/stone_slab_from_stone_stonecutting": {
    "criteria": {
      "has_stone": "2020-05-02 23:02:14 -0700"
    },
    "done": true
  },
  "minecraft:end/elytra": {
    "criteria": {
      "elytra": "2020-05-02 23:24:52 -0700"
    },
    "done": true
  },
  "minecraft:recipes/decorations/magenta_stained_glass_pane": {
    "criteria": {
      "has_glass": "2020-05-09 20:07:43 -0700"
    },
    "done": true
  },
  "minecraft:recipes/building_blocks/chiseled_stone_bricks_stone_from_stonecutting": {
    "criteria": {
      "has_stone": "2020-05-02 23:02:14 -0700"
    },
    "done": true
  },
  "minecraft:recipes/tools/wooden_shovel": {
    "criteria": {
      "has_stick": "2020-05-02 22:49:36 -0700"
    },
    "done": true
  },
  "minecraft:recipes/decorations/torch": {
    "criteria": {
      "has_stone_pickaxe": "2020-05-14 15:56:14 -0700"
    },
    "done": true
  },
  "minecraft:recipes/combat/diamond_sword": {
    "criteria": {
      "has_diamond": "2020-04-26 21:09:17 -0700"
    },
    "done": true
  },
  "minecraft:recipes/decorations/black_carpet_from_white_carpet": {
    "criteria": {
      "has_black_dye": "2020-05-01 22:22:08 -0700"
    },
    "done": true
  },
  "minecraft:recipes/decorations/purple_carpet_from_white_carpet": {
    "criteria": {
      "has_white_carpet": "2020-05-02 23:37:53 -0700"
    },
    "done": true
  },
  "minecraft:recipes/decorations/cyan_stained_glass_pane": {
    "criteria": {
      "has_glass": "2020-05-09 20:07:43 -0700"
    },
    "done": true
  },
  "minecraft:recipes/building_blocks/blue_stained_glass": {
    "criteria": {
      "has_glass": "2020-05-09 20:07:43 -0700"
    },
    "done": true
  },
  "minecraft:recipes/decorations/red_carpet_from_white_carpet": {
    "criteria": {
      "has_red_dye": "2020-04-26 21:20:53 -0700"
    },
    "done": true
  },
  "minecraft:recipes/misc/stick": {
    "criteria": {
      "has_planks": "2020-05-14 15:54:34 -0700"
    },
    "done": true
  },
  "minecraft:recipes/building_blocks/stone_brick_slab_from_stone_stonecutting": {
    "criteria": {
      "has_stone": "2020-05-02 23:02:14 -0700"
    },
    "done": true
  },
  "minecraft:recipes/transportation/spruce_boat": {
    "criteria": {
      "in_water": "2020-04-21 21:52:31 -0700"
    },
    "done": true
  },
  "minecraft:recipes/decorations/jukebox": {
    "criteria": {
      "has_diamond": "2020-04-26 21:09:17 -0700"
    },
    "done": true
  },
  "minecraft:recipes/building_blocks/smooth_sandstone_stairs_from_smooth_sandstone_stonecutting": {
    "criteria": {
      "has_mossy_cobblestone": "2020-05-02 23:37:46 -0700"
    },
    "done": true
  },
  "minecraft:recipes/tools/flint_and_steel": {
    "criteria": {
      "has_obsidian": "2020-05-04 23:58:45 -0700"
    },
    "done": true
  },
  "minecraft:recipes/redstone/dispenser": {
    "criteria": {
      "has_bow": "2020-05-01 21:55:38 -0700"
    },
    "done": true
  },
  "minecraft:recipes/building_blocks/quartz_stairs_from_quartz_block_stonecutting": {
    "criteria": {
      "has_quartz_block": "2020-05-02 22:25:01 -0700"
    },
    "done": true
  },
  "minecraft:recipes/building_blocks/smooth_quartz_slab_from_smooth_quartz_stonecutting": {
    "criteria": {
      "has_smooth_quartz": "2020-05-04 23:37:00 -0700"
    },
    "done": true
  },
  "minecraft:recipes/decorations/light_blue_glazed_terracotta": {
    "criteria": {
      "has_light_blue_terracotta": "2020-05-01 21:23:01 -0700"
    },
    "done": true
  },
  "minecraft:recipes/food/mushroom_stew": {
    "criteria": {
      "has_red_mushroom": "2020-04-26 21:09:29 -0700"
    },
    "done": true
  },
  "minecraft:recipes/building_blocks/emerald_block": {
    "criteria": {
      "has_emerald": "2020-05-04 23:06:29 -0700"
    },
    "done": true
  },
  "minecraft:recipes/transportation/detector_rail": {
    "criteria": {
      "has_rail": "2020-05-04 23:13:36 -0700"
    },
    "done": true
  },
  "minecraft:husbandry/balanced_diet": {
    "criteria": {
      "cooked_beef": "2020-05-01 22:08:36 -0700",
      "potato": "2020-05-01 21:58:24 -0700",
      "cookie": "2020-05-14 15:16:24 -0700"
    },
    "done": false
  },
  "minecraft:recipes/brewing/golden_carrot": {
    "criteria": {
      "has_gold_nugget": "2020-04-26 21:09:25 -0700"
    },
    "done": true
  },
  "minecraft:recipes/tools/wooden_hoe": {
    "criteria": {
      "has_stick": "2020-05-02 22:49:36 -0700"
    },
    "done": true
  },
  "minecraft:recipes/building_blocks/smooth_sandstone_slab_from_smooth_sandstone_stonecutting": {
    "criteria": {
      "has_smooth_sandstone": "2020-05-02 23:37:46 -0700"
    },
    "done": true
  },
  "minecraft:recipes/building_blocks/cobblestone_slab": {
    "criteria": {
      "has_cobblestone": "2020-05-14 15:55:32 -0700"
    },
    "done": true
  },
  "minecraft:recipes/redstone/trapped_chest": {
    "criteria": {
      "has_tripwire_hook": "2020-05-02 22:32:42 -0700"
    },
    "done": true
  },
  "minecraft:recipes/building_blocks/diorite_slab": {
    "criteria": {
      "has_diorite": "2020-05-02 22:33:27 -0700"
    },
    "done": true
  },
  "minecraft:recipes/building_blocks/cobblestone_stairs": {
    "criteria": {
      "has_cobblestone": "2020-05-14 15:55:32 -0700"
    },
    "done": true
  },
  "minecraft:recipes/building_blocks/birch_slab": {
    "criteria": {
      "has_planks": "2020-05-14 15:54:34 -0700"
    },
    "done": true
  },
  "minecraft:recipes/decorations/orange_stained_glass_pane": {
    "criteria": {
      "has_glass": "2020-05-09 20:07:43 -0700"
    },
    "done": true
  },
  "minecraft:recipes/building_blocks/polished_diorite_slab_from_diorite_stonecutting": {
    "criteria": {
      "has_diorite": "2020-05-04 23:38:13 -0700"
    },
    "done": true
  },
  "minecraft:recipes/misc/creeper_banner_pattern": {
    "criteria": {
      "has_creeper_head": "2020-05-04 21:59:34 -0700"
    },
    "done": true
  },
  "minecraft:recipes/misc/lime_dye": {
    "criteria": {
      "has_white_dye": "2020-05-02 22:50:30 -0700"
    },
    "done": true
  },
  "minecraft:recipes/misc/magenta_dye_from_blue_red_white_dye": {
    "criteria": {
      "has_rose_red": "2020-04-26 21:20:53 -0700"
    },
    "done": true
  },
  "minecraft:recipes/redstone/tnt": {
    "criteria": {
      "has_gunpowder": "2020-05-01 22:21:50 -0700"
    },
    "done": true
  },
  "minecraft:nether/get_wither_skull": {
    "criteria": {
      "wither_skull": "2020-05-02 23:31:28 -0700"
    },
    "done": true
  },
  "minecraft:recipes/redstone/lectern": {
    "criteria": {
      "has_book": "2020-05-08 19:41:49 -0700"
    },
    "done": true
  },
  "minecraft:recipes/decorations/black_stained_glass_pane": {
    "criteria": {
      "has_glass": "2020-05-09 20:07:43 -0700"
    },
    "done": true
  },
  "minecraft:recipes/misc/composter": {
    "criteria": {
      "has_wood_slab": "2020-05-02 22:59:23 -0700"
    },
    "done": true
  },
  "minecraft:recipes/building_blocks/yellow_stained_glass": {
    "criteria": {
      "has_glass": "2020-05-09 20:07:43 -0700"
    },
    "done": true
  },
  "minecraft:recipes/building_blocks/smooth_stone_slab": {
    "criteria": {
      "has_smooth_stone": "2020-05-02 22:18:44 -0700"
    },
    "done": true
  },
  "minecraft:recipes/building_blocks/stone_stairs_from_stone_stonecutting": {
    "criteria": {
      "has_stone": "2020-05-02 23:02:14 -0700"
    },
    "done": true
  },
  "minecraft:husbandry/bred_all_animals": {
    "criteria": {
      "minecraft:fox": "2020-05-02 23:42:15 -0700"
    },
    "done": false
  },
  "minecraft:recipes/building_blocks/andesite_stairs_from_andesite_stonecutting": {
    "criteria": {
      "has_andesite": "2020-05-09 20:07:21 -0700"
    },
    "done": true
  },
  "minecraft:recipes/decorations/diorite_wall_from_diorite_stonecutting": {
    "criteria": {
      "has_diorite": "2020-05-02 22:33:27 -0700"
    },
    "done": true
  },
  "minecraft:recipes/building_blocks/brick_stairs": {
    "criteria": {
      "has_brick_block": "2020-05-02 22:18:17 -0700"
    },
    "done": true
  },
  "minecraft:recipes/combat/diamond_chestplate": {
    "criteria": {
      "has_diamond": "2020-04-26 21:09:17 -0700"
    },
    "done": true
  },
  "minecraft:story/mine_stone": {
    "criteria": {
      "get_stone": "2020-05-14 15:55:32 -0700"
    },
    "done": true
  },
  "minecraft:recipes/decorations/cyan_carpet_from_white_carpet": {
    "criteria": {
      "has_white_carpet": "2020-05-02 23:37:53 -0700"
    },
    "done": true
  },
  "minecraft:recipes/decorations/furnace": {
    "criteria": {
      "has_cobblestone": "2020-05-14 15:55:32 -0700"
    },
    "done": true
  },
  "minecraft:recipes/brewing/cauldron": {
    "criteria": {
      "has_water_bucket": "2020-05-02 23:44:17 -0700"
    },
    "done": true
  },
  "minecraft:recipes/combat/diamond_leggings": {
    "criteria": {
      "has_diamond": "2020-04-26 21:09:17 -0700"
    },
    "done": true
  },
  "minecraft:recipes/decorations/armor_stand": {
    "criteria": {
      "has_stone_slab": "2020-05-01 21:23:01 -0700"
    },
    "done": true
  },
  "minecraft:recipes/decorations/gray_stained_glass_pane": {
    "criteria": {
      "has_glass": "2020-05-09 20:07:43 -0700"
    },
    "done": true
  },
  "minecraft:recipes/misc/charcoal": {
    "criteria": {
      "has_log": "2020-05-02 23:25:53 -0700"
    },
    "done": true
  },
  "minecraft:recipes/building_blocks/andesite_stairs": {
    "criteria": {
      "has_andesite": "2020-05-09 20:07:21 -0700"
    },
    "done": true
  },
  "minecraft:recipes/building_blocks/red_stained_glass": {
    "criteria": {
      "has_glass": "2020-05-09 20:07:43 -0700"
    },
    "done": true
  },
  "minecraft:recipes/decorations/green_stained_glass_pane": {
    "criteria": {
      "has_glass": "2020-05-09 20:07:43 -0700"
    },
    "done": true
  },
  "minecraft:recipes/tools/wooden_pickaxe": {
    "criteria": {
      "has_stick": "2020-05-02 22:49:36 -0700"
    },
    "done": true
  },
  "minecraft:story/lava_bucket": {
    "criteria": {
      "lava_bucket": "2020-05-02 23:02:21 -0700"
    },
    "done": true
  },
  "minecraft:recipes/building_blocks/cobblestone_slab_from_cobblestone_stonecutting": {
    "criteria": {
      "has_cobblestone": "2020-05-14 15:55:32 -0700"
    },
    "done": true
  },
  "minecraft:husbandry/root": {
    "criteria": {
      "consumed_item": "2020-05-01 21:58:24 -0700"
    },
    "done": true
  },
  "minecraft:recipes/transportation/birch_boat": {
    "criteria": {
      "in_water": "2020-04-21 21:52:31 -0700"
    },
    "done": true
  },
  "minecraft:recipes/building_blocks/quartz_stairs": {
    "criteria": {
      "has_quartz_block": "2020-05-02 22:25:01 -0700"
    },
    "done": true
  },
  "minecraft:recipes/building_blocks/polished_diorite_slab": {
    "criteria": {
      "has_polished_diorite": "2020-05-04 23:38:13 -0700"
    },
    "done": true
  },
  "minecraft:recipes/building_blocks/polished_andesite_slab_from_andesite_stonecutting": {
    "criteria": {
      "has_andesite": "2020-05-09 20:07:21 -0700"
    },
    "done": true
  },
  "minecraft:recipes/decorations/enchanting_table": {
    "criteria": {
      "has_obsidian": "2020-05-04 23:58:45 -0700"
    },
    "done": true
  },
  "minecraft:recipes/building_blocks/polished_andesite_from_andesite_stonecutting": {
    "criteria": {
      "has_andesite": "2020-05-09 20:07:21 -0700"
    },
    "done": true
  },
  "minecraft:recipes/transportation/acacia_boat": {
    "criteria": {
      "in_water": "2020-04-21 21:52:31 -0700"
    },
    "done": true
  },
  "minecraft:recipes/decorations/light_blue_carpet_from_white_carpet": {
    "criteria": {
      "has_light_blue_dye": "2020-05-02 22:51:50 -0700"
    },
    "done": true
  },
  "minecraft:recipes/decorations/birch_sign": {
    "criteria": {
      "has_birch_planks": "2020-05-14 15:54:34 -0700"
    },
    "done": true
  },
  "minecraft:recipes/building_blocks/smooth_quartz_slab": {
    "criteria": {
      "has_smooth_quartz": "2020-05-04 23:37:00 -0700"
    },
    "done": true
  },
  "minecraft:recipes/building_blocks/orange_stained_glass": {
    "criteria": {
      "has_glass": "2020-05-09 20:07:43 -0700"
    },
    "done": true
  },
  "minecraft:adventure/root": {
    "criteria": {
      "killed_something": "2020-04-21 22:54:39 -0700"
    },
    "done": true
  },
  "minecraft:recipes/misc/bowl": {
    "criteria": {
      "has_red_mushroom": "2020-04-26 21:09:29 -0700"
    },
    "done": true
  },
  "minecraft:recipes/building_blocks/stone_brick_stairs_from_stone_stonecutting": {
    "criteria": {
      "has_stone": "2020-05-02 23:02:14 -0700"
    },
    "done": true
  },
  "minecraft:recipes/tools/stone_hoe": {
    "criteria": {
      "has_cobblestone": "2020-05-14 15:55:32 -0700"
    },
    "done": true
  },
  "minecraft:recipes/decorations/green_glazed_terracotta": {
    "criteria": {
      "has_green_terracotta": "2020-05-02 23:37:52 -0700"
    },
    "done": true
  },
  "minecraft:recipes/tools/diamond_pickaxe": {
    "criteria": {
      "has_diamond": "2020-04-26 21:09:17 -0700"
    },
    "done": true
  },
  "minecraft:recipes/tools/diamond_hoe": {
    "criteria": {
      "has_diamond": "2020-04-26 21:09:17 -0700"
    },
    "done": true
  },
  "minecraft:recipes/food/baked_potato_from_smoking": {
    "criteria": {
      "has_potato": "2020-04-26 21:20:23 -0700"
    },
    "done": true
  },
  "minecraft:recipes/transportation/activator_rail": {
    "criteria": {
      "has_rail": "2020-05-04 23:13:36 -0700"
    },
    "done": true
  },
  "minecraft:recipes/decorations/white_stained_glass_pane": {
    "criteria": {
      "has_glass": "2020-05-09 20:07:43 -0700"
    },
    "done": true
  },
  "minecraft:recipes/tools/diamond_shovel": {
    "criteria": {
      "has_diamond": "2020-04-26 21:09:17 -0700"
    },
    "done": true
  },
  "minecraft:adventure/kill_all_mobs": {
    "criteria": {
      "minecraft:pillager": "2020-05-01 22:09:01 -0700",
      "minecraft:zombie_pigman": "2020-05-01 22:05:46 -0700",
      "minecraft:vindicator": "2020-05-01 22:09:31 -0700",
      "minecraft:phantom": "2020-05-01 22:12:18 -0700",
      "minecraft:zombie": "2020-05-01 21:57:57 -0700"
    },
    "done": false
  },
  "minecraft:recipes/building_blocks/chiseled_quartz_block_from_quartz_block_stonecutting": {
    "criteria": {
      "has_quartz_block": "2020-05-02 22:25:01 -0700"
    },
    "done": true
  },
  "minecraft:adventure/whos_the_pillager_now": {
    "criteria": {
      "kill_pillager": "2020-05-01 22:09:01 -0700"
    },
    "done": true
  },
  "minecraft:recipes/food/baked_potato": {
    "criteria": {
      "has_potato": "2020-04-26 21:20:23 -0700"
    },
    "done": true
  },
  "minecraft:recipes/building_blocks/smooth_sandstone_stairs": {
    "criteria": {
      "has_smooth_sandstone": "2020-05-02 23:37:46 -0700"
    },
    "done": true
  },
  "minecraft:recipes/building_blocks/lime_stained_glass": {
    "criteria": {
      "has_glass": "2020-05-09 20:07:43 -0700"
    },
    "done": true
  },
  "minecraft:recipes/decorations/pink_stained_glass_pane": {
    "criteria": {
      "has_glass": "2020-05-09 20:07:43 -0700"
    },
    "done": true
  },
  "minecraft:recipes/decorations/black_stained_glass_pane_from_glass_pane": {
    "criteria": {
      "has_black_dye": "2020-05-01 22:22:08 -0700"
    },
    "done": true
  },
  "minecraft:recipes/decorations/lime_carpet_from_white_carpet": {
    "criteria": {
      "has_white_carpet": "2020-05-02 23:37:53 -0700"
    },
    "done": true
  },
  "minecraft:recipes/decorations/magenta_carpet_from_white_carpet": {
    "criteria": {
      "has_white_carpet": "2020-05-02 23:37:53 -0700"
    },
    "done": true
  },
  "minecraft:recipes/misc/iron_nugget_from_smelting": {
    "criteria": {
      "has_chainmail_chestplate": "2020-04-21 22:40:28 -0700"
    },
    "done": true
  },
  "minecraft:recipes/building_blocks/dark_prismarine_slab": {
    "criteria": {
      "has_dark_prismarine": "2020-05-04 22:04:50 -0700"
    },
    "done": true
  },
  "minecraft:adventure/voluntary_exile": {
    "criteria": {
      "voluntary_exile": "2020-05-01 22:10:23 -0700"
    },
    "done": true
  },
  "minecraft:recipes/redstone/birch_door": {
    "criteria": {
      "has_planks": "2020-05-14 15:54:34 -0700"
    },
    "done": true
  },
  "minecraft:recipes/building_blocks/polished_diorite_stairs_from_polished_diorite_stonecutting": {
    "criteria": {
      "has_polished_diorite": "2020-05-04 23:38:13 -0700"
    },
    "done": true
  },
  "minecraft:recipes/building_blocks/quartz_pillar_from_quartz_block_stonecutting": {
    "criteria": {
      "has_quartz_block": "2020-05-02 22:25:01 -0700"
    },
    "done": true
  },
  "minecraft:recipes/decorations/brick_wall_from_bricks_stonecutting": {
    "criteria": {
      "has_bricks": "2020-05-02 22:18:17 -0700"
    },
    "done": true
  },
  "minecraft:recipes/decorations/glass_pane": {
    "criteria": {
      "has_glass": "2020-05-09 20:07:43 -0700"
    },
    "done": true
  },
  "minecraft:recipes/misc/gold_ingot_from_nuggets": {
    "criteria": {
      "has_gold_nugget": "2020-04-26 21:09:25 -0700"
    },
    "done": true
  },
  "minecraft:recipes/building_blocks/smooth_quartz": {
    "criteria": {
      "has_quartz_block": "2020-05-02 22:25:01 -0700"
    },
    "done": true
  },
  "minecraft:recipes/building_blocks/polished_diorite_stairs": {
    "criteria": {
      "has_polished_diorite": "2020-05-04 23:38:13 -0700"
    },
    "done": true
  },
  "minecraft:recipes/building_blocks/magenta_stained_glass": {
    "criteria": {
      "has_glass": "2020-05-09 20:07:43 -0700"
    },
    "done": true
  },
  "minecraft:story/mine_diamond": {
    "criteria": {
      "diamond": "2020-04-26 21:09:17 -0700"
    },
    "done": true
  },
  "minecraft:story/upgrade_tools": {
    "criteria": {
      "stone_pickaxe": "2020-05-14 15:56:14 -0700"
    },
    "done": true
  },
  "minecraft:recipes/misc/light_blue_dye_from_blue_white_dye": {
    "criteria": {
      "has_white_dye": "2020-05-02 22:50:30 -0700"
    },
    "done": true
  },
  "minecraft:recipes/combat/diamond_helmet": {
    "criteria": {
      "has_diamond": "2020-04-26 21:09:17 -0700"
    },
    "done": true
  },
  "minecraft:recipes/decorations/green_carpet_from_white_carpet": {
    "criteria": {
      "has_white_carpet": "2020-05-02 23:37:53 -0700"
    },
    "done": true
  },
  "minecraft:recipes/decorations/red_stained_glass_pane_from_glass_pane": {
    "criteria": {
      "has_red_dye": "2020-04-26 21:20:53 -0700"
    },
    "done": true
  },
  "minecraft:recipes/transportation/oak_boat": {
    "criteria": {
      "in_water": "2020-04-21 21:52:31 -0700"
    },
    "done": true
  },
  "minecraft:recipes/building_blocks/light_blue_stained_glass": {
    "criteria": {
      "has_glass": "2020-05-09 20:07:43 -0700"
    },
    "done": true
  },
  "minecraft:recipes/decorations/birch_fence": {
    "criteria": {
      "has_planks": "2020-05-14 15:54:34 -0700"
    },
    "done": true
  },
  "minecraft:recipes/food/baked_potato_from_campfire_cooking": {
    "criteria": {
      "has_potato": "2020-04-26 21:20:23 -0700"
    },
    "done": true
  },
  "minecraft:recipes/decorations/light_gray_carpet_from_white_carpet": {
    "criteria": {
      "has_light_gray_dye": "2020-05-02 22:50:00 -0700"
    },
    "done": true
  },
  "minecraft:recipes/decorations/blue_stained_glass_pane": {
    "criteria": {
      "has_glass": "2020-05-09 20:07:43 -0700"
    },
    "done": true
  },
  "minecraft:recipes/building_blocks/smooth_stone_slab_from_smooth_stone_stonecutting": {
    "criteria": {
      "has_smooth_stone": "2020-05-02 22:18:44 -0700"
    },
    "done": true
  },
  "minecraft:recipes/misc/pink_dye_from_red_white_dye": {
    "criteria": {
      "has_red_dye": "2020-04-26 21:20:53 -0700"
    },
    "done": true
  },
  "minecraft:recipes/decorations/honey_block": {
    "criteria": {
      "has_honey_bottle": "2020-05-02 23:27:40 -0700"
    },
    "done": true
  },
  "minecraft:recipes/tools/wooden_axe": {
    "criteria": {
      "has_stick": "2020-05-02 22:49:36 -0700"
    },
    "done": true
  },
  "minecraft:recipes/decorations/cyan_glazed_terracotta": {
    "criteria": {
      "has_cyan_terracotta": "2020-05-02 22:36:02 -0700"
    },
    "done": true
  },
  "minecraft:recipes/brewing/blaze_powder": {
    "criteria": {
      "has_blaze_rod": "2020-04-26 21:20:56 -0700"
    },
    "done": true
  },
  "minecraft:recipes/building_blocks/polished_diorite_stairs_from_diorite_stonecutting": {
    "criteria": {
      "has_diorite": "2020-05-04 23:38:13 -0700"
    },
    "done": true
  },
  "minecraft:recipes/building_blocks/stone_bricks_from_stone_stonecutting": {
    "criteria": {
      "has_stone": "2020-05-02 23:02:14 -0700"
    },
    "done": true
  },
  "minecraft:recipes/tools/diamond_axe": {
    "criteria": {
      "has_diamond": "2020-04-26 21:09:17 -0700"
    },
    "done": true
  },
  "minecraft:recipes/building_blocks/diorite_stairs_from_diorite_stonecutting": {
    "criteria": {
      "has_diorite": "2020-05-02 22:33:27 -0700"
    },
    "done": true
  },
  "minecraft:recipes/brewing/glass_bottle": {
    "criteria": {
      "has_glass": "2020-05-09 20:07:43 -0700"
    },
    "done": true
  },
  "minecraft:recipes/decorations/light_blue_stained_glass_pane": {
    "criteria": {
      "has_glass": "2020-05-09 20:07:43 -0700"
    },
    "done": true
  },
  "minecraft:recipes/building_blocks/polished_diorite_slab_from_polished_diorite_stonecutting": {
    "criteria": {
      "has_polished_diorite": "2020-05-04 23:38:13 -0700"
    },
    "done": true
  },
  "minecraft:recipes/decorations/light_gray_bed": {
    "criteria": {
      "has_light_gray_wool": "2020-05-02 22:49:33 -0700"
    },
    "done": true
  },
  "minecraft:recipes/redstone/birch_button": {
    "criteria": {
      "has_planks": "2020-05-14 15:54:34 -0700"
    },
    "done": true
  },
  "minecraft:recipes/building_blocks/quartz_slab": {
    "criteria": {
      "has_quartz_block": "2020-05-02 22:25:01 -0700"
    },
    "done": true
  },
  "minecraft:recipes/decorations/painting": {
    "criteria": {
      "has_wool": "2020-05-02 22:49:33 -0700"
    },
    "done": true
  },
  "minecraft:recipes/building_blocks/white_stained_glass": {
    "criteria": {
      "has_glass": "2020-05-09 20:07:43 -0700"
    },
    "done": true
  },
  "minecraft:recipes/building_blocks/stone_slab": {
    "criteria": {
      "has_stone": "2020-05-02 23:02:14 -0700"
    },
    "done": true
  },
  "minecraft:recipes/building_blocks/andesite_slab_from_andesite_stonecutting": {
    "criteria": {
      "has_andesite": "2020-05-09 20:07:21 -0700"
    },
    "done": true
  },
  "minecraft:recipes/misc/lime_dye_from_smelting": {
    "criteria": {
      "has_sea_pickle": "2020-04-21 22:12:07 -0700"
    },
    "done": true
  },
  "minecraft:recipes/building_blocks/green_stained_glass": {
    "criteria": {
      "has_glass": "2020-05-09 20:07:43 -0700"
    },
    "done": true
  },
  "minecraft:recipes/combat/wooden_sword": {
    "criteria": {
      "has_stick": "2020-05-02 22:49:36 -0700"
    },
    "done": true
  },
  "minecraft:recipes/tools/stone_shovel": {
    "criteria": {
      "has_cobblestone": "2020-05-14 15:55:32 -0700"
    },
    "done": true
  },
  "minecraft:recipes/decorations/yellow_stained_glass_pane": {
    "criteria": {
      "has_glass": "2020-05-09 20:07:43 -0700"
    },
    "done": true
  },
  "minecraft:recipes/decorations/light_gray_banner": {
    "criteria": {
      "has_light_gray_wool": "2020-05-02 22:49:33 -0700"
    },
    "done": true
  },
  "minecraft:recipes/building_blocks/diorite_stairs": {
    "criteria": {
      "has_diorite": "2020-05-02 22:33:27 -0700"
    },
    "done": true
  },
  "minecraft:recipes/building_blocks/cyan_stained_glass": {
    "criteria": {
      "has_glass": "2020-05-09 20:07:43 -0700"
    },
    "done": true
  },
  "minecraft:recipes/building_blocks/bookshelf": {
    "criteria": {
      "has_book": "2020-05-08 19:41:49 -0700"
    },
    "done": true
  },
  "minecraft:recipes/building_blocks/andesite": {
    "criteria": {
      "has_stone": "2020-05-02 22:33:27 -0700"
    },
    "done": true
  },
  "minecraft:recipes/building_blocks/polished_andesite_stairs_from_polished_andesite_stonecutting": {
    "criteria": {
      "has_polished_andesite": "2020-05-04 21:50:42 -0700"
    },
    "done": true
  },
  "minecraft:recipes/building_blocks/sea_lantern": {
    "criteria": {
      "has_prismarine_crystals": "2020-05-04 23:59:36 -0700"
    },
    "done": true
  },
  "minecraft:recipes/building_blocks/jungle_planks": {
    "criteria": {
      "has_log": "2020-05-02 23:38:18 -0700"
    },
    "done": true
  },
  "minecraft:recipes/building_blocks/quartz_slab_from_stonecutting": {
    "criteria": {
      "has_quartz_block": "2020-05-02 22:25:01 -0700"
    },
    "done": true
  },
  "minecraft:recipes/decorations/brown_carpet_from_white_carpet": {
    "criteria": {
      "has_white_carpet": "2020-05-02 23:37:53 -0700"
    },
    "done": true
  },
  "minecraft:recipes/building_blocks/chiseled_quartz_block": {
    "criteria": {
      "has_quartz_block": "2020-05-02 22:25:01 -0700"
    },
    "done": true
  },
  "minecraft:recipes/decorations/white_stained_glass_pane_from_glass_pane": {
    "criteria": {
      "has_white_dye": "2020-05-02 22:50:30 -0700"
    },
    "done": true
  },
  "minecraft:recipes/building_blocks/birch_planks": {
    "criteria": {
      "has_log": "2020-05-02 23:25:53 -0700"
    },
    "done": true
  },
  "minecraft:recipes/building_blocks/brick_slab_from_bricks_stonecutting": {
    "criteria": {
      "has_bricks": "2020-05-02 22:18:17 -0700"
    },
    "done": true
  },
  "minecraft:recipes/misc/skull_banner_pattern": {
    "criteria": {
      "has_wither_skeleton_skull": "2020-05-02 23:31:28 -0700"
    },
    "done": true
  },
  "minecraft:recipes/decorations/orange_carpet_from_white_carpet": {
    "criteria": {
      "has_white_carpet": "2020-05-02 23:37:53 -0700"
    },
    "done": true
  },
  "minecraft:recipes/redstone/birch_fence_gate": {
    "criteria": {
      "has_planks": "2020-05-14 15:54:34 -0700"
    },
    "done": true
  },
  "minecraft:story/root": {
    "criteria": {
      "crafting_table": "2020-05-02 22:42:57 -0700"
    },
    "done": true
  },
  "minecraft:recipes/building_blocks/smooth_quartz_stairs": {
    "criteria": {
      "has_smooth_quartz": "2020-05-04 23:37:00 -0700"
    },
    "done": true
  },
  "minecraft:recipes/redstone/stone_button": {
    "criteria": {
      "has_stone": "2020-05-02 23:02:14 -0700"
    },
    "done": true
  },
  "minecraft:recipes/combat/crossbow": {
    "criteria": {
      "has_tripwire_hook": "2020-05-02 22:32:42 -0700"
    },
    "done": true
  },
  "minecraft:recipes/building_blocks/polished_diorite_from_diorite_stonecutting": {
    "criteria": {
      "has_diorite": "2020-05-02 22:33:27 -0700"
    },
    "done": true
  },
  "minecraft:story/form_obsidian": {
    "criteria": {
      "obsidian": "2020-05-04 23:58:45 -0700"
    },
    "done": true
  },
  "minecraft:recipes/brewing/brewing_stand": {
    "criteria": {
      "has_blaze_rod": "2020-04-26 21:20:56 -0700"
    },
    "done": true
  },
  "minecraft:recipes/misc/iron_nugget_from_blasting": {
    "criteria": {
      "has_chainmail_chestplate": "2020-04-21 22:40:28 -0700"
    },
    "done": true
  },
  "minecraft:recipes/building_blocks/smooth_sandstone_slab": {
    "criteria": {
      "has_smooth_sandstone": "2020-05-02 23:37:46 -0700"
    },
    "done": true
  },
  "minecraft:recipes/building_blocks/acacia_planks": {
    "criteria": {
      "has_logs": "2020-05-02 23:25:55 -0700"
    },
    "done": true
  },
  "minecraft:adventure/kill_a_mob": {
    "criteria": {
      "minecraft:zombie": "2020-05-01 21:57:57 -0700"
    },
    "done": true
  },
  "minecraft:recipes/misc/magenta_dye_from_blue_red_pink": {
    "criteria": {
      "has_red_dye": "2020-04-26 21:20:53 -0700"
    },
    "done": true
  },
  "minecraft:recipes/decorations/diorite_wall": {
    "criteria": {
      "has_diorite": "2020-05-02 22:33:27 -0700"
    },
    "done": true
  },
  "minecraft:recipes/decorations/blue_carpet_from_white_carpet": {
    "criteria": {
      "has_white_carpet": "2020-05-02 23:37:53 -0700"
    },
    "done": true
  },
  "minecraft:nether/obtain_blaze_rod": {
    "criteria": {
      "blaze_rod": "2020-04-26 21:20:56 -0700"
    },
    "done": true
  },
  "minecraft:adventure/ol_betsy": {
    "criteria": {
      "shot_crossbow": "2020-05-01 21:38:06 -0700"
    },
    "done": true
  },
  "minecraft:recipes/building_blocks/stone": {
    "criteria": {
      "has_cobblestone": "2020-05-14 15:55:32 -0700"
    },
    "done": true
  },
  "minecraft:recipes/building_blocks/polished_andesite": {
    "criteria": {
      "has_stone": "2020-05-09 20:07:21 -0700"
    },
    "done": true
  },
  "minecraft:recipes/decorations/stonecutter": {
    "criteria": {
      "has_stone": "2020-05-02 23:02:14 -0700"
    },
    "done": true
  },
  "minecraft:recipes/misc/gray_dye": {
    "criteria": {
      "has_black_dye": "2020-05-01 22:22:08 -0700"
    },
    "done": true
  },
  "minecraft:recipes/building_blocks/smooth_quartz_stairs_from_smooth_quartz_stonecutting": {
    "criteria": {
      "has_smooth_quartz": "2020-05-04 23:37:00 -0700"
    },
    "done": true
  },
  "minecraft:adventure/adventuring_time": {
    "criteria": {
      "minecraft:plains": "2020-04-21 21:41:35 -0700"
    },
    "done": false
  },
  "minecraft:recipes/misc/book": {
    "criteria": {
      "has_paper": "2020-05-01 22:21:52 -0700"
    },
    "done": true
  },
  "minecraft:recipes/decorations/light_gray_carpet": {
    "criteria": {
      "has_light_gray_wool": "2020-05-02 22:49:33 -0700"
    },
    "done": true
  },
  "minecraft:recipes/combat/stone_sword": {
    "criteria": {
      "has_cobblestone": "2020-05-14 15:55:32 -0700"
    },
    "done": true
  },
  "minecraft:recipes/decorations/barrel": {
    "criteria": {
      "has_wood_slab": "2020-05-02 22:59:23 -0700"
    },
    "done": true
  },
  "minecraft:recipes/transportation/powered_rail": {
    "criteria": {
      "has_rail": "2020-05-04 23:13:36 -0700"
    },
    "done": true
  },
  "minecraft:recipes/decorations/cobblestone_wall": {
    "criteria": {
      "has_cobblestone": "2020-05-14 15:55:32 -0700"
    },
    "done": true
  },
  "minecraft:recipes/tools/stone_pickaxe": {
    "criteria": {
      "has_cobblestone": "2020-05-14 15:55:32 -0700"
    },
    "done": true
  },
  "minecraft:recipes/misc/iron_ingot_from_nuggets": {
    "criteria": {
      "has_iron_nugget": "2020-04-26 21:09:19 -0700"
    },
    "done": true
  },
  "minecraft:recipes/redstone/stone_pressure_plate": {
    "criteria": {
      "has_stone": "2020-05-02 23:02:14 -0700"
    },
    "done": true
  },
  "minecraft:recipes/building_blocks/brown_stained_glass": {
    "criteria": {
      "has_glass": "2020-05-09 20:07:43 -0700"
    },
    "done": true
  },
  "minecraft:recipes/misc/purple_dye": {
    "criteria": {
      "has_red_dye": "2020-04-26 21:20:53 -0700"
    },
    "done": true
  },
  "minecraft:recipes/transportation/jungle_boat": {
    "criteria": {
      "in_water": "2020-04-21 21:52:31 -0700"
    },
    "done": true
  },
  "minecraft:recipes/misc/red_dye_from_tulip": {
    "criteria": {
      "has_red_flower": "2020-04-26 21:09:32 -0700"
    },
    "done": true
  },
  "minecraft:adventure/shoot_arrow": {
    "criteria": {
      "shot_arrow": "2020-05-01 21:44:38 -0700"
    },
    "done": true
  },
  "minecraft:recipes/decorations/cobblestone_wall_from_cobblestone_stonecutting": {
    "criteria": {
      "has_cobblestone": "2020-05-14 15:55:32 -0700"
    },
    "done": true
  },
  "minecraft:recipes/decorations/stone_brick_walls_from_stone_stonecutting": {
    "criteria": {
      "has_stone": "2020-05-02 23:02:14 -0700"
    },
    "done": true
  },
  "minecraft:recipes/misc/sugar_from_honey_bottle": {
    "criteria": {
      "has_honey_bottle": "2020-05-02 23:27:40 -0700"
    },
    "done": true
  },
  "minecraft:recipes/building_blocks/polished_andesite_slab_from_polished_andesite_stonecutting": {
    "criteria": {
      "has_polished_andesite": "2020-05-04 21:50:42 -0700"
    },
    "done": true
  },
  "minecraft:recipes/building_blocks/birch_stairs": {
    "criteria": {
      "has_planks": "2020-05-14 15:54:34 -0700"
    },
    "done": true
  },
  "minecraft:recipes/decorations/grindstone": {
    "criteria": {
      "has_stone_slab": "2020-05-05 00:11:26 -0700"
    },
    "done": true
  },
  "minecraft:recipes/building_blocks/light_gray_stained_glass": {
    "criteria": {
      "has_glass": "2020-05-09 20:07:43 -0700"
    },
    "done": true
  },
  "minecraft:recipes/building_blocks/diamond_block": {
    "criteria": {
      "has_diamond": "2020-04-26 21:09:17 -0700"
    },
    "done": true
  },
  "minecraft:recipes/transportation/dark_oak_boat": {
    "criteria": {
      "in_water": "2020-04-21 21:52:31 -0700"
    },
    "done": true
  },
  "minecraft:recipes/building_blocks/dark_prismarine_stairs": {
    "criteria": {
      "has_dark_prismarine": "2020-05-04 22:04:50 -0700"
    },
    "done": true
  },
  "minecraft:recipes/decorations/andesite_wall_from_andesite_stonecutting": {
    "criteria": {
      "has_andesite": "2020-05-09 20:07:21 -0700"
    },
    "done": true
  },
  "minecraft:recipes/decorations/red_stained_glass_pane": {
    "criteria": {
      "has_glass": "2020-05-09 20:07:43 -0700"
    },
    "done": true
  },
  "minecraft:recipes/misc/light_gray_dye_from_gray_white_dye": {
    "criteria": {
      "has_white_dye": "2020-05-02 22:50:30 -0700"
    },
    "done": true
  },
  "minecraft:recipes/building_blocks/brick_slab": {
    "criteria": {
      "has_brick_block": "2020-05-02 22:18:17 -0700"
    },
    "done": true
  },
  "minecraft:husbandry/breed_an_animal": {
    "criteria": {
      "bred": "2020-05-02 23:42:15 -0700"
    },
    "done": true
  },
  "minecraft:recipes/redstone/birch_trapdoor": {
    "criteria": {
      "has_planks": "2020-05-14 15:54:34 -0700"
    },
    "done": true
  },
  "minecraft:recipes/decorations/lantern": {
    "criteria": {
      "has_iron_nugget": "2020-04-26 21:09:19 -0700"
    },
    "done": true
  },
  "minecraft:recipes/building_blocks/stone_stairs": {
    "criteria": {
      "has_stone": "2020-05-02 23:02:14 -0700"
    },
    "done": true
  },
  "minecraft:recipes/decorations/light_gray_stained_glass_pane_from_glass_pane": {
    "criteria": {
      "has_light_gray_dye": "2020-05-02 22:50:00 -0700"
    },
    "done": true
  },
  "minecraft:recipes/decorations/brown_stained_glass_pane": {
    "criteria": {
      "has_glass": "2020-05-09 20:07:43 -0700"
    },
    "done": true
  },
  "minecraft:recipes/decorations/yellow_carpet_from_white_carpet": {
    "criteria": {
      "has_white_carpet": "2020-05-02 23:37:53 -0700"
    },
    "done": true
  },
  "minecraft:recipes/combat/diamond_boots": {
    "criteria": {
      "has_diamond": "2020-04-26 21:09:17 -0700"
    },
    "done": true
  },
  "minecraft:recipes/building_blocks/polished_diorite": {
    "criteria": {
      "has_stone": "2020-05-02 22:33:27 -0700"
    },
    "done": true
  },
  "minecraft:recipes/decorations/light_blue_stained_glass_pane_from_glass_pane": {
    "criteria": {
      "has_light_blue_dye": "2020-05-02 22:51:50 -0700"
    },
    "done": true
  },
  "minecraft:recipes/decorations/andesite_wall": {
    "criteria": {
      "has_andesite": "2020-05-09 20:07:21 -0700"
    },
    "done": true
  },
  "minecraft:recipes/building_blocks/andesite_slab": {
    "criteria": {
      "has_andesite": "2020-05-09 20:07:21 -0700"
    },
    "done": true
  },
  "minecraft:recipes/decorations/gray_carpet_from_white_carpet": {
    "criteria": {
      "has_white_carpet": "2020-05-02 23:37:53 -0700"
    },
    "done": true
  },
  "minecraft:recipes/misc/orange_dye_from_red_yellow": {
    "criteria": {
      "has_red_dye": "2020-04-26 21:20:53 -0700"
    },
    "done": true
  },
  "minecraft:recipes/decorations/pink_carpet_from_white_carpet": {
    "criteria": {
      "has_white_carpet": "2020-05-02 23:37:53 -0700"
    },
    "done": true
  },
  "minecraft:recipes/tools/stone_axe": {
    "criteria": {
      "has_cobblestone": "2020-05-14 15:55:32 -0700"
    },
    "done": true
  },
  "minecraft:recipes/misc/light_gray_dye_from_black_white_dye": {
    "criteria": {
      "has_black_dye": "2020-05-01 22:22:08 -0700"
    },
    "done": true
  },
  "minecraft:recipes/building_blocks/pink_stained_glass": {
    "criteria": {
      "has_glass": "2020-05-09 20:07:43 -0700"
    },
    "done": true
  },
  "minecraft:recipes/decorations/light_gray_stained_glass_pane": {
    "criteria": {
      "has_glass": "2020-05-09 20:07:43 -0700"
    },
    "done": true
  },
  "DataVersion": 2230
}